castepxbin/__init__.py
castepxbin/castep_bin.py
castepxbin/ome_bin.py
castepxbin/pdos.py
castepxbin/wave.py
castepxbin-0.3.1.dist-info/licenses/LICENSE
castepxbin-0.3.1.dist-info/WHEEL
castepxbin-0.3.1.dist-info/METADATA
castepxbin-0.3.1.dist-info/RECORD
